wuwa_mcp_server/__init__.py
wuwa_mcp_server/builders/__init__.py
wuwa_mcp_server/builders/markdown_builder.py
wuwa_mcp_server/builders/markdown_formatter.py
wuwa_mcp_server/core/__init__.py
wuwa_mcp_server/core/config.py
wuwa_mcp_server/core/container.py
wuwa_mcp_server/core/exceptions.py
wuwa_mcp_server/core/interfaces.py
wuwa_mcp_server/core/logging_config.py
wuwa_mcp_server/domain/__init__.py
wuwa_mcp_server/domain/entities.py
wuwa_mcp_server/domain/value_objects.py
wuwa_mcp_server/infrastructure/__init__.py
wuwa_mcp_server/infrastructure/api/__init__.py
wuwa_mcp_server/infrastructure/api/http_client.py
wuwa_mcp_server/infrastructure/api/kuro_api_client.py
wuwa_mcp_server/infrastructure/repositories/__init__.py
wuwa_mcp_server/infrastructure/repositories/artifact_repository.py
wuwa_mcp_server/infrastructure/repositories/base_repository.py
wuwa_mcp_server/infrastructure/repositories/character_repository.py
wuwa_mcp_server/parsers/__init__.py
wuwa_mcp_server/parsers/content_parser.py
wuwa_mcp_server/parsers/html_converter.py
wuwa_mcp_server/parsers/strategies/__init__.py
wuwa_mcp_server/parsers/strategies/artifact_strategy.py
wuwa_mcp_server/parsers/strategies/base_strategy.py
wuwa_mcp_server/parsers/strategies/character_strategy.py
wuwa_mcp_server/parsers/strategies/strategy_content_strategy.py
wuwa_mcp_server/server.py
wuwa_mcp_server/services/__init__.py
wuwa_mcp_server/services/artifact_service.py
wuwa_mcp_server/services/character_service.py
wuwa_mcp_server/services/markdown_service.py
wuwa_mcp_server-2.0.1.dist-info/WHEEL
wuwa_mcp_server-2.0.1.dist-info/entry_points.txt
wuwa_mcp_server-2.0.1.dist-info/METADATA
wuwa_mcp_server-2.0.1.dist-info/RECORD
