Metadata-Version: 2.3
Name: wuwa-mcp-server
Version: 2.0.1
Summary: Add your description here
Requires-Dist: asyncio>=3.4.3
Requires-Dist: beautifulsoup4>=4.13.4
Requires-Dist: httpx>=0.28.1
Requires-Dist: mcp[cli]>=1.8.0
Requires-Dist: smithery>=0.1.23
Requires-Dist: uvicorn>=0.32.1
Requires-Dist: starlette>=0.41.3
Requires-Dist: ruff>=0.8.0 ; extra == 'dev'
Requires-Python: >=3.12
Provides-Extra: dev
